arm_pytorch_utilities/__init__.py
arm_pytorch_utilities/array_utils.py
arm_pytorch_utilities/cache.py
arm_pytorch_utilities/controller.py
arm_pytorch_utilities/draw.py
arm_pytorch_utilities/gmm.py
arm_pytorch_utilities/grad.py
arm_pytorch_utilities/linalg.py
arm_pytorch_utilities/load_data.py
arm_pytorch_utilities/math_utils.py
arm_pytorch_utilities/optim.py
arm_pytorch_utilities/preprocess.py
arm_pytorch_utilities/rand.py
arm_pytorch_utilities/serialization.py
arm_pytorch_utilities/simulation.py
arm_pytorch_utilities/softknn.py
arm_pytorch_utilities/str_utils.py
arm_pytorch_utilities/tensor_utils.py
arm_pytorch_utilities/trajectory.py
arm_pytorch_utilities/make_data/__init__.py
arm_pytorch_utilities/make_data/datasource.py
arm_pytorch_utilities/make_data/make.py
arm_pytorch_utilities/make_data/params.py
arm_pytorch_utilities/make_data/select.py
arm_pytorch_utilities/model/__init__.py
arm_pytorch_utilities/model/common.py
arm_pytorch_utilities/model/make.py
arm_pytorch_utilities/model/mdn.py
arm_pytorch_utilities/policy/__init__.py
arm_pytorch_utilities/policy/lin_gauss.py
arm_pytorch_utilities-0.4.3.dist-info/LICENSE.txt
arm_pytorch_utilities-0.4.3.dist-info/METADATA
arm_pytorch_utilities-0.4.3.dist-info/WHEEL
arm_pytorch_utilities-0.4.3.dist-info/top_level.txt
arm_pytorch_utilities-0.4.3.dist-info/RECORD
