Metadata-Version: 2.1
Name: arm_pytorch_utilities
Version: 0.4.3
Summary: Utilities for working with pytorch
Author-email: Sheng Zhong <zhsh@umich.edu>
Maintainer-email: Sheng Zhong <zhsh@umich.edu>
License: Copyright (c) 2023 University of Michigan ARM Lab
Project-URL: Homepage, https://github.com/UM-ARM-Lab/arm_pytorch_utilities
Project-URL: Bug Reports, https://github.com/UM-ARM-Lab/arm_pytorch_utilities/issues
Project-URL: Source, https://github.com/UM-ARM-Lab/arm_pytorch_utilities
Keywords: rng,pytorch,visualization
Classifier: Development Status :: 4 - Beta
Classifier: Intended Audience :: Developers
Classifier: License :: OSI Approved :: MIT License
Classifier: Programming Language :: Python :: 3
Classifier: Programming Language :: Python :: 3 :: Only
Requires-Python: >=3.6
License-File: LICENSE.txt
Requires-Dist: torch
Requires-Dist: numpy
Requires-Dist: matplotlib
Requires-Dist: scipy
Requires-Dist: pytorch-seed
Provides-Extra: test
Requires-Dist: pytest ; extra == 'test'
